Workbook

Sheet AAPL_Valu
B3: Evaluation Summary
B6: Company Name | I6: Mic | J6: Ticker | K6: Last Price
B7: Apple Inc | I7: XNAS | J7: AAPL | K7: 250.12
B8: Apple Inc. designs, manufactures, and markets smartphones, personal computers, tablets, wearables, and accessories worldwide. The company offers iPhone, a line of smartphones; Mac, a line of personal computers; iPad, a line of multi-purpose tablets; and wearables, home, and accessories comprising AirPods, Apple Vision Pro, Apple TV, Apple Watch, Beats products, and HomePod, as well as Apple branded and third-party accessories. It also provides AppleCare support and cloud services; and operates various platforms, including the App Store that allow customers to discover and download applications and digital content, such as books, music, video, games, and podcasts, as well as advertising services include third-party licensing arrangements and its own advertising platforms. In addition, the company offers various subscription-based services, such as Apple Arcade, a game subscription service; Apple Fitness+, a personalized fitness service; Apple Music, which offers users a curated listening experience with on-demand radio stations; Apple News+, a subscription news and magazine service; Apple TV, which offers exclusive original content and live sports; Apple Card, a co-branded credit card; and Apple Pay, a cashless payment service, as well as licenses its intellectual property. The company serves consumers, and small and mid-sized businesses; and the education, enterprise, and government markets. It distributes third-party applications for its products through the App Store. The company also sells its products through its retail and online stores, and direct sales force; and third-party cellular network carriers and resellers. The company was formerly known as Apple Computer, Inc. and changed its name to Apple Inc. in January 2007. Apple Inc. was founded in 1976 and is headquartered in Cupertino, California.
B20: Historical Evaluation | F20: Recent Evaluation | J20: Custom Evaluation
B21: WACC | C21: =AAPL_Custom_DCF!$G$43 | F21: WACC | G21: =AAPL_Recent_DCF!$G$43 | J21: WACC | K21: =AAPL_Historical_DCF!$G$43
B22: Fair Price | C22: =AAPL_Custom_DCF!$C$40 | F22: Fair Price | G22: =AAPL_Recent_DCF!$C$40 | J22: Fair Price | K22: =AAPL_Historical_DCF!$C$40
B23: Under / Over | C23: =AAPL_Custom_DCF!$C$42 | F23: Under / Over | G23: =AAPL_Recent_DCF!$C$42 | J23: Under / Over | K23: =AAPL_Historical_DCF!$C$42
B25: Summary
B26: AAPL Appears to Be: | E26: =IF(AVERAGE((C22-K7)/K7, (G22-K7)/K7, (K22-K7)/K7) >1, "Highly Under Valued", IF(AND(AVERAGE((C22-K7)/K7, (G22-K7)/K7, (K22-K7)/K7) >0.1, AVERAGE((C22-K7)/K7, (G22-K7)/K7, (K22-K7)/K7) < 1), "Moderately Under Valued", IF(AND(AVERAGE((C22-K7)/K7, (G22-K7)/K7, (K22-K7)/K7) <=0.1, AVERAGE((C22-K7)/K7, (G22-K7)/K7, (K22-K7)/K7) >= -0.1), "Fairly Valued", IF(AND(AVERAGE((C22-K7)/K7, (G22-K7)/K7, (K22-K7)/K7) < -0.1, AVERAGE((C22-K7)/K7, (G22-K7)/K7, (K22-K7)/K7) > -1), "Moderately Over Valued", IF(AVERAGE((C22-K7)/K7, (G22-K7)/K7, (K22-K7)/K7) < 1, "Highly Over Valued", "")))))

Sheet Model_Assumptions
B3: Evaluation Inputs
B6: Base Inputs
B7: Projected Years | C7: Rapid Growth Length | D7: Forecast Period Length | E7: Terminal Growth Rate | F7: Expected Market Rate of Return | G7: Expected Risk Free Rate of Return
B8: 5 | C8: =B8-D8 | D8: 5 | E8: 0.02 | F8: 0.065 | G8: 0.04
B11: Custom
B12: Metric | C12: Rapid Growth Period | D12: Forecast Period | E12: Terminal Period
B13: Sales Growth | C13: 0.039186366 | D13: =C13 | E13: =E8
B14: Effective Tax Rate | C14: 0.15610002 | D14: =C14 | E14: =C14
B15: EBITDA : Revenue (%) | C15: 0.34216355 | D15: =C15 | E15: =C15
B16: Depreciaiton : Revenue (%) | C16: 0.028429631 | D16: =C16 | E16: =C16
B17: Working Capital : Revenue (%) | C17: -0.036217392 | D17: =C17 | E17: =C17
B18: CAPEX : Revenue (%) | C18: 0.029037986 | D18: =C18 | E18: =C18
B19: WACC | C19: =AAPL_Custom_DCF!$G$43
B20: Fair Price | C20: =AAPL_Custom_DCF!$C$40
B21: Under / Over | C21: =AAPL_Custom_DCF!$C$42
B24: Recent
B25: Metric | C25: Rapid Growth Period | D25: Forecast Period | E25: Terminal Period
B26: Sales Growth | C26: 0.064255118 | D26: =C26 | E26: =E8
B27: Effective Tax Rate | C27: 0.15610002 | D27: =C27 | E27: =C27
B28: EBITDA : Revenue (%) | C28: 0.34781731 | D28: =C28 | E28: =C28
B29: Depreciaiton : Revenue (%) | C29: 0.028109313 | D29: =C29 | E29: =C29
B30: Working Capital : Revenue (%) | C30: -0.060072904 | D30: =C30 | E30: =C30
B31: CAPEX : Revenue (%) | C31: 0.030553079 | D31: =C31 | E31: =C31
B32: WACC | C32: =AAPL_Recent_DCF!$G$43
B33: Fair Price | C33: =AAPL_Recent_DCF!$C$40
B34: Under / Over | C34: =AAPL_Recent_DCF!$C$42
B37: Historical
B38: Metric | C38: Rapid Growth Period | D38: Forecast Period | E38: Terminal Period
B39: Sales Growth | C39: 0.014117613 | D39: =C39 | E39: =E8
B40: Effective Tax Rate | C40: 0.17365857 | D40: =C40 | E40: =C40
B41: EBITDA : Revenue (%) | C41: 0.3365098 | D41: =C41 | E41: =C41
B42: Depreciaiton : Revenue (%) | C42: 0.028749949 | D42: =C42 | E42: =C42
B43: Working Capital : Revenue (%) | C43: -0.012361879 | D43: =C43 | E43: =C43
B44: CAPEX : Revenue (%) | C44: 0.027522892 | D44: =C44 | E44: =C44
B45: WACC | C45: =AAPL_Historical_DCF!$G$43
B46: Fair Price | C46: =AAPL_Historical_DCF!$C$40
B47: Under / Over | C47: =AAPL_Historical_DCF!$C$42

Sheet AAPL_Historical_DCF
B3: Historical Evaluation
B6: Evaluation Assumptions
B7: Metric | C7: Rapid Growth Period | D7: Forecast Period | E7: Terminal Period
B8: Sales Growth | C8: ='Model_Assumptions'!C39 | D8: ='Model_Assumptions'!D39 | E8: ='Model_Assumptions'!E39
B9: Effective Tax Rate | C9: ='Model_Assumptions'!C40 | D9: ='Model_Assumptions'!D40 | E9: ='Model_Assumptions'!E40
B10: EBITDA : Revenue (%) | C10: ='Model_Assumptions'!C41 | D10: ='Model_Assumptions'!D41 | E10: ='Model_Assumptions'!E41
B11: Depreciaiton : Revenue (%) | C11: ='Model_Assumptions'!C42 | D11: ='Model_Assumptions'!D42 | E11: ='Model_Assumptions'!E42
B12: Working Capital : Revenue (%) | C12: ='Model_Assumptions'!C43 | D12: ='Model_Assumptions'!D43 | E12: ='Model_Assumptions'!E43
B13: CAPEX : Revenue (%) | C13: ='Model_Assumptions'!C44 | D13: ='Model_Assumptions'!D44 | E13: ='Model_Assumptions'!E44
B15: Cash Flows | D15: =IF(Model_Assumptions!$C$8 = 0, $D$7, $C$7) | E15: =IF(E16=Model_Assumptions!$C$8 +1, $D$7, IF(E16 = Model_Assumptions!$B$8+1, $E$7, "")) | F15: =IF(F16=Model_Assumptions!$C$8 +1, $D$7, IF(F16 = Model_Assumptions!$B$8+1, $E$7, "")) | G15: =IF(G16=Model_Assumptions!$C$8 +1, $D$7, IF(G16 = Model_Assumptions!$B$8+1, $E$7, "")) | H15: =IF(H16=Model_Assumptions!$C$8 +1, $D$7, IF(H16 = Model_Assumptions!$B$8+1, $E$7, "")) | I15: =IF(I16=Model_Assumptions!$C$8 +1, $D$7, IF(I16 = Model_Assumptions!$B$8+1, $E$7, "")) | J15: =IF(J16=Model_Assumptions!$C$8 +1, $D$7, IF(J16 = Model_Assumptions!$B$8+1, $E$7, "")) | K15: =IF(K16=Model_Assumptions!$C$8 +1, $D$7, IF(K16 = Model_Assumptions!$B$8+1, $E$7, "")) | L15: =IF(L16=Model_Assumptions!$C$8 +1, $D$7, IF(L16 = Model_Assumptions!$B$8+1, $E$7, "")) | ... CM15: =IF(CM16=Model_Assumptions!$C$8 +1, $D$7, IF(CM16 = Model_Assumptions!$B$8+1, $E$7, ""))
B16: Year | C16: =0 | D16: =IF(C16<'Model_Assumptions'!$B$8+1,C16+1, "") | E16: =IF(D16<'Model_Assumptions'!$B$8+1,D16+1, "") | F16: =IF(E16<'Model_Assumptions'!$B$8+1,E16+1, "") | G16: =IF(F16<'Model_Assumptions'!$B$8+1,F16+1, "") | H16: =IF(G16<'Model_Assumptions'!$B$8+1,G16+1, "") | I16: =IF(H16<'Model_Assumptions'!$B$8+1,H16+1, "") | J16: =IF(I16<'Model_Assumptions'!$B$8+1,I16+1, "") | K16: =IF(J16<'Model_Assumptions'!$B$8+1,J16+1, "") | ... CM16: =IF(CL16<'Model_Assumptions'!$B$8+1,CL16+1, "")
B17: Revenue | C17: 416161000000 | D17: =IF(D$16="","",IF(D$16=('Model_Assumptions'!$B$8 +1),C$17*(1+$E$8),IF(D$16<='Model_Assumptions'!$C$8,C$17*(1+$C$8),IF(D$16>=('Model_Assumptions'!$C$8+1),C$17*(1+$D$8),"")))) | E17: =IF(E$16="","",IF(E$16=('Model_Assumptions'!$B$8 +1),D$17*(1+$E$8),IF(E$16<='Model_Assumptions'!$C$8,D$17*(1+$C$8),IF(E$16>=('Model_Assumptions'!$C$8+1),D$17*(1+$D$8),"")))) | F17: =IF(F$16="","",IF(F$16=('Model_Assumptions'!$B$8 +1),E$17*(1+$E$8),IF(F$16<='Model_Assumptions'!$C$8,E$17*(1+$C$8),IF(F$16>=('Model_Assumptions'!$C$8+1),E$17*(1+$D$8),"")))) | G17: =IF(G$16="","",IF(G$16=('Model_Assumptions'!$B$8 +1),F$17*(1+$E$8),IF(G$16<='Model_Assumptions'!$C$8,F$17*(1+$C$8),IF(G$16>=('Model_Assumptions'!$C$8+1),F$17*(1+$D$8),"")))) | H17: =IF(H$16="","",IF(H$16=('Model_Assumptions'!$B$8 +1),G$17*(1+$E$8),IF(H$16<='Model_Assumptions'!$C$8,G$17*(1+$C$8),IF(H$16>=('Model_Assumptions'!$C$8+1),G$17*(1+$D$8),"")))) | I17: =IF(I$16="","",IF(I$16=('Model_Assumptions'!$B$8 +1),H$17*(1+$E$8),IF(I$16<='Model_Assumptions'!$C$8,H$17*(1+$C$8),IF(I$16>=('Model_Assumptions'!$C$8+1),H$17*(1+$D$8),"")))) | J17: =IF(J$16="","",IF(J$16=('Model_Assumptions'!$B$8 +1),I$17*(1+$E$8),IF(J$16<='Model_Assumptions'!$C$8,I$17*(1+$C$8),IF(J$16>=('Model_Assumptions'!$C$8+1),I$17*(1+$D$8),"")))) | K17: =IF(K$16="","",IF(K$16=('Model_Assumptions'!$B$8 +1),J$17*(1+$E$8),IF(K$16<='Model_Assumptions'!$C$8,J$17*(1+$C$8),IF(K$16>=('Model_Assumptions'!$C$8+1),J$17*(1+$D$8),"")))) | ... CM17: =IF(CM$16="","",IF(CM$16=('Model_Assumptions'!$B$8 +1),CL$17*(1+$E$8),IF(CM$16<='Model_Assumptions'!$C$8,CL$17*(1+$C$8),IF(CM$16>=('Model_Assumptions'!$C$8+1),CL$17*(1+$D$8),""))))
B18: EBITDA | D18: =IF(D$16="","",IF(D$16=('Model_Assumptions'!$B$8+1), D$17*$E$10,IF(D$16<='Model_Assumptions'!$C$8,D$17*$C$10,IF(D$16>=('Model_Assumptions'!$C$8 + 1), D$17*$D$10, "")))) | E18: =IF(E$16="","",IF(E$16=('Model_Assumptions'!$B$8+1), E$17*$E$10,IF(E$16<='Model_Assumptions'!$C$8,E$17*$C$10,IF(E$16>=('Model_Assumptions'!$C$8 + 1), E$17*$D$10, "")))) | F18: =IF(F$16="","",IF(F$16=('Model_Assumptions'!$B$8+1), F$17*$E$10,IF(F$16<='Model_Assumptions'!$C$8,F$17*$C$10,IF(F$16>=('Model_Assumptions'!$C$8 + 1), F$17*$D$10, "")))) | G18: =IF(G$16="","",IF(G$16=('Model_Assumptions'!$B$8+1), G$17*$E$10,IF(G$16<='Model_Assumptions'!$C$8,G$17*$C$10,IF(G$16>=('Model_Assumptions'!$C$8 + 1), G$17*$D$10, "")))) | H18: =IF(H$16="","",IF(H$16=('Model_Assumptions'!$B$8+1), H$17*$E$10,IF(H$16<='Model_Assumptions'!$C$8,H$17*$C$10,IF(H$16>=('Model_Assumptions'!$C$8 + 1), H$17*$D$10, "")))) | I18: =IF(I$16="","",IF(I$16=('Model_Assumptions'!$B$8+1), I$17*$E$10,IF(I$16<='Model_Assumptions'!$C$8,I$17*$C$10,IF(I$16>=('Model_Assumptions'!$C$8 + 1), I$17*$D$10, "")))) | J18: =IF(J$16="","",IF(J$16=('Model_Assumptions'!$B$8+1), J$17*$E$10,IF(J$16<='Model_Assumptions'!$C$8,J$17*$C$10,IF(J$16>=('Model_Assumptions'!$C$8 + 1), J$17*$D$10, "")))) | K18: =IF(K$16="","",IF(K$16=('Model_Assumptions'!$B$8+1), K$17*$E$10,IF(K$16<='Model_Assumptions'!$C$8,K$17*$C$10,IF(K$16>=('Model_Assumptions'!$C$8 + 1), K$17*$D$10, "")))) | ... CM18: =IF(CM$16="","",IF(CM$16=('Model_Assumptions'!$B$8+1), CM$17*$E$10,IF(CM$16<='Model_Assumptions'!$C$8,CM$17*$C$10,IF(CM$16>=('Model_Assumptions'!$C$8 + 1), CM$17*$D$10, ""))))
B19: EBITDA After Tax | D19: =IF(D$16="","", IF(D$16=('Model_Assumptions'!$B$8+1), D$18*(1-$E$9),IF(D$16<='Model_Assumptions'!$C$8,D$18*(1-$C$9),IF(D$16>=('Model_Assumptions'!$C$8 + 1), D$18*(1-$D$9), "")))) | E19: =IF(E$16="","", IF(E$16=('Model_Assumptions'!$B$8+1), E$18*(1-$E$9),IF(E$16<='Model_Assumptions'!$C$8,E$18*(1-$C$9),IF(E$16>=('Model_Assumptions'!$C$8 + 1), E$18*(1-$D$9), "")))) | F19: =IF(F$16="","", IF(F$16=('Model_Assumptions'!$B$8+1), F$18*(1-$E$9),IF(F$16<='Model_Assumptions'!$C$8,F$18*(1-$C$9),IF(F$16>=('Model_Assumptions'!$C$8 + 1), F$18*(1-$D$9), "")))) | G19: =IF(G$16="","", IF(G$16=('Model_Assumptions'!$B$8+1), G$18*(1-$E$9),IF(G$16<='Model_Assumptions'!$C$8,G$18*(1-$C$9),IF(G$16>=('Model_Assumptions'!$C$8 + 1), G$18*(1-$D$9), "")))) | H19: =IF(H$16="","", IF(H$16=('Model_Assumptions'!$B$8+1), H$18*(1-$E$9),IF(H$16<='Model_Assumptions'!$C$8,H$18*(1-$C$9),IF(H$16>=('Model_Assumptions'!$C$8 + 1), H$18*(1-$D$9), "")))) | I19: =IF(I$16="","", IF(I$16=('Model_Assumptions'!$B$8+1), I$18*(1-$E$9),IF(I$16<='Model_Assumptions'!$C$8,I$18*(1-$C$9),IF(I$16>=('Model_Assumptions'!$C$8 + 1), I$18*(1-$D$9), "")))) | J19: =IF(J$16="","", IF(J$16=('Model_Assumptions'!$B$8+1), J$18*(1-$E$9),IF(J$16<='Model_Assumptions'!$C$8,J$18*(1-$C$9),IF(J$16>=('Model_Assumptions'!$C$8 + 1), J$18*(1-$D$9), "")))) | K19: =IF(K$16="","", IF(K$16=('Model_Assumptions'!$B$8+1), K$18*(1-$E$9),IF(K$16<='Model_Assumptions'!$C$8,K$18*(1-$C$9),IF(K$16>=('Model_Assumptions'!$C$8 + 1), K$18*(1-$D$9), "")))) | ... CM19: =IF(CM$16="","", IF(CM$16=('Model_Assumptions'!$B$8+1), CM$18*(1-$E$9),IF(CM$16<='Model_Assumptions'!$C$8,CM$18*(1-$C$9),IF(CM$16>=('Model_Assumptions'!$C$8 + 1), CM$18*(1-$D$9), ""))))
B20: Depreciation | D20: =IF(D$16="","",IF(D$16=('Model_Assumptions'!$B$8+1), D$17*$E$11,IF(D$16<='Model_Assumptions'!$C$8,D$17*$C$11,IF(D$16>=('Model_Assumptions'!$C$8 + 1), D$17*$D$11, "")))) | E20: =IF(E$16="","",IF(E$16=('Model_Assumptions'!$B$8+1), E$17*$E$11,IF(E$16<='Model_Assumptions'!$C$8,E$17*$C$11,IF(E$16>=('Model_Assumptions'!$C$8 + 1), E$17*$D$11, "")))) | F20: =IF(F$16="","",IF(F$16=('Model_Assumptions'!$B$8+1), F$17*$E$11,IF(F$16<='Model_Assumptions'!$C$8,F$17*$C$11,IF(F$16>=('Model_Assumptions'!$C$8 + 1), F$17*$D$11, "")))) | G20: =IF(G$16="","",IF(G$16=('Model_Assumptions'!$B$8+1), G$17*$E$11,IF(G$16<='Model_Assumptions'!$C$8,G$17*$C$11,IF(G$16>=('Model_Assumptions'!$C$8 + 1), G$17*$D$11, "")))) | H20: =IF(H$16="","",IF(H$16=('Model_Assumptions'!$B$8+1), H$17*$E$11,IF(H$16<='Model_Assumptions'!$C$8,H$17*$C$11,IF(H$16>=('Model_Assumptions'!$C$8 + 1), H$17*$D$11, "")))) | I20: =IF(I$16="","",IF(I$16=('Model_Assumptions'!$B$8+1), I$17*$E$11,IF(I$16<='Model_Assumptions'!$C$8,I$17*$C$11,IF(I$16>=('Model_Assumptions'!$C$8 + 1), I$17*$D$11, "")))) | J20: =IF(J$16="","",IF(J$16=('Model_Assumptions'!$B$8+1), J$17*$E$11,IF(J$16<='Model_Assumptions'!$C$8,J$17*$C$11,IF(J$16>=('Model_Assumptions'!$C$8 + 1), J$17*$D$11, "")))) | K20: =IF(K$16="","",IF(K$16=('Model_Assumptions'!$B$8+1), K$17*$E$11,IF(K$16<='Model_Assumptions'!$C$8,K$17*$C$11,IF(K$16>=('Model_Assumptions'!$C$8 + 1), K$17*$D$11, "")))) | ... CM20: =IF(CM$16="","",IF(CM$16=('Model_Assumptions'!$B$8+1), CM$17*$E$11,IF(CM$16<='Model_Assumptions'!$C$8,CM$17*$C$11,IF(CM$16>=('Model_Assumptions'!$C$8 + 1), CM$17*$D$11, ""))))
B21: Depreciation Tax Shield | D21: =IF(D$16 = "","", IF(D$16 =( 'Model_Assumptions'!$B$8 +1), D$20 * $E$9, IF(D$16 <= 'Model_Assumptions'!$C$8, D$20 * $C$9, IF(D$16 >= ('Model_Assumptions'!$C$8 + 1), D$20 * $D$9)))) | E21: =IF(E$16 = "","", IF(E$16 =( 'Model_Assumptions'!$B$8 +1), E$20 * $E$9, IF(E$16 <= 'Model_Assumptions'!$C$8, E$20 * $C$9, IF(E$16 >= ('Model_Assumptions'!$C$8 + 1), E$20 * $D$9)))) | F21: =IF(F$16 = "","", IF(F$16 =( 'Model_Assumptions'!$B$8 +1), F$20 * $E$9, IF(F$16 <= 'Model_Assumptions'!$C$8, F$20 * $C$9, IF(F$16 >= ('Model_Assumptions'!$C$8 + 1), F$20 * $D$9)))) | G21: =IF(G$16 = "","", IF(G$16 =( 'Model_Assumptions'!$B$8 +1), G$20 * $E$9, IF(G$16 <= 'Model_Assumptions'!$C$8, G$20 * $C$9, IF(G$16 >= ('Model_Assumptions'!$C$8 + 1), G$20 * $D$9)))) | H21: =IF(H$16 = "","", IF(H$16 =( 'Model_Assumptions'!$B$8 +1), H$20 * $E$9, IF(H$16 <= 'Model_Assumptions'!$C$8, H$20 * $C$9, IF(H$16 >= ('Model_Assumptions'!$C$8 + 1), H$20 * $D$9)))) | I21: =IF(I$16 = "","", IF(I$16 =( 'Model_Assumptions'!$B$8 +1), I$20 * $E$9, IF(I$16 <= 'Model_Assumptions'!$C$8, I$20 * $C$9, IF(I$16 >= ('Model_Assumptions'!$C$8 + 1), I$20 * $D$9)))) | J21: =IF(J$16 = "","", IF(J$16 =( 'Model_Assumptions'!$B$8 +1), J$20 * $E$9, IF(J$16 <= 'Model_Assumptions'!$C$8, J$20 * $C$9, IF(J$16 >= ('Model_Assumptions'!$C$8 + 1), J$20 * $D$9)))) | K21: =IF(K$16 = "","", IF(K$16 =( 'Model_Assumptions'!$B$8 +1), K$20 * $E$9, IF(K$16 <= 'Model_Assumptions'!$C$8, K$20 * $C$9, IF(K$16 >= ('Model_Assumptions'!$C$8 + 1), K$20 * $D$9)))) | ... CM21: =IF(CM$16 = "","", IF(CM$16 =( 'Model_Assumptions'!$B$8 +1), CM$20 * $E$9, IF(CM$16 <= 'Model_Assumptions'!$C$8, CM$20 * $C$9, IF(CM$16 >= ('Model_Assumptions'!$C$8 + 1), CM$20 * $D$9))))
B22: Change in Working Capital | D22: =IF(D$16="","",IF(D$16=('Model_Assumptions'!$B$8+1),( D$17-C$17)*$E$12,IF(D$16<='Model_Assumptions'!$C$8,( D$17-C$17)*$C$12,IF(D$16>=('Model_Assumptions'!$C$8 + 1), ( D$17-C$17)*$D$12, "")))) | E22: =IF(E$16="","",IF(E$16=('Model_Assumptions'!$B$8+1),( E$17-D$17)*$E$12,IF(E$16<='Model_Assumptions'!$C$8,( E$17-D$17)*$C$12,IF(E$16>=('Model_Assumptions'!$C$8 + 1), ( E$17-D$17)*$D$12, "")))) | F22: =IF(F$16="","",IF(F$16=('Model_Assumptions'!$B$8+1),( F$17-E$17)*$E$12,IF(F$16<='Model_Assumptions'!$C$8,( F$17-E$17)*$C$12,IF(F$16>=('Model_Assumptions'!$C$8 + 1), ( F$17-E$17)*$D$12, "")))) | G22: =IF(G$16="","",IF(G$16=('Model_Assumptions'!$B$8+1),( G$17-F$17)*$E$12,IF(G$16<='Model_Assumptions'!$C$8,( G$17-F$17)*$C$12,IF(G$16>=('Model_Assumptions'!$C$8 + 1), ( G$17-F$17)*$D$12, "")))) | H22: =IF(H$16="","",IF(H$16=('Model_Assumptions'!$B$8+1),( H$17-G$17)*$E$12,IF(H$16<='Model_Assumptions'!$C$8,( H$17-G$17)*$C$12,IF(H$16>=('Model_Assumptions'!$C$8 + 1), ( H$17-G$17)*$D$12, "")))) | I22: =IF(I$16="","",IF(I$16=('Model_Assumptions'!$B$8+1),( I$17-H$17)*$E$12,IF(I$16<='Model_Assumptions'!$C$8,( I$17-H$17)*$C$12,IF(I$16>=('Model_Assumptions'!$C$8 + 1), ( I$17-H$17)*$D$12, "")))) | J22: =IF(J$16="","",IF(J$16=('Model_Assumptions'!$B$8+1),( J$17-I$17)*$E$12,IF(J$16<='Model_Assumptions'!$C$8,( J$17-I$17)*$C$12,IF(J$16>=('Model_Assumptions'!$C$8 + 1), ( J$17-I$17)*$D$12, "")))) | K22: =IF(K$16="","",IF(K$16=('Model_Assumptions'!$B$8+1),( K$17-J$17)*$E$12,IF(K$16<='Model_Assumptions'!$C$8,( K$17-J$17)*$C$12,IF(K$16>=('Model_Assumptions'!$C$8 + 1), ( K$17-J$17)*$D$12, "")))) | ... CM22: =IF(CM$16="","",IF(CM$16=('Model_Assumptions'!$B$8+1),( CM$17-CL$17)*$E$12,IF(CM$16<='Model_Assumptions'!$C$8,( CM$17-CL$17)*$C$12,IF(CM$16>=('Model_Assumptions'!$C$8 + 1), ( CM$17-CL$17)*$D$12, ""))))
B23: Capital Expenditures | D23: =IF(D$16="","",IF(D$16=('Model_Assumptions'!$B$8+1), D$17*$E$13,IF(D$16<='Model_Assumptions'!$C$8,D$17*$C$13,IF(D$16>=('Model_Assumptions'!$C$8 + 1), D$17*$D$13, "")))) | E23: =IF(E$16="","",IF(E$16=('Model_Assumptions'!$B$8+1), E$17*$E$13,IF(E$16<='Model_Assumptions'!$C$8,E$17*$C$13,IF(E$16>=('Model_Assumptions'!$C$8 + 1), E$17*$D$13, "")))) | F23: =IF(F$16="","",IF(F$16=('Model_Assumptions'!$B$8+1), F$17*$E$13,IF(F$16<='Model_Assumptions'!$C$8,F$17*$C$13,IF(F$16>=('Model_Assumptions'!$C$8 + 1), F$17*$D$13, "")))) | G23: =IF(G$16="","",IF(G$16=('Model_Assumptions'!$B$8+1), G$17*$E$13,IF(G$16<='Model_Assumptions'!$C$8,G$17*$C$13,IF(G$16>=('Model_Assumptions'!$C$8 + 1), G$17*$D$13, "")))) | H23: =IF(H$16="","",IF(H$16=('Model_Assumptions'!$B$8+1), H$17*$E$13,IF(H$16<='Model_Assumptions'!$C$8,H$17*$C$13,IF(H$16>=('Model_Assumptions'!$C$8 + 1), H$17*$D$13, "")))) | I23: =IF(I$16="","",IF(I$16=('Model_Assumptions'!$B$8+1), I$17*$E$13,IF(I$16<='Model_Assumptions'!$C$8,I$17*$C$13,IF(I$16>=('Model_Assumptions'!$C$8 + 1), I$17*$D$13, "")))) | J23: =IF(J$16="","",IF(J$16=('Model_Assumptions'!$B$8+1), J$17*$E$13,IF(J$16<='Model_Assumptions'!$C$8,J$17*$C$13,IF(J$16>=('Model_Assumptions'!$C$8 + 1), J$17*$D$13, "")))) | K23: =IF(K$16="","",IF(K$16=('Model_Assumptions'!$B$8+1), K$17*$E$13,IF(K$16<='Model_Assumptions'!$C$8,K$17*$C$13,IF(K$16>=('Model_Assumptions'!$C$8 + 1), K$17*$D$13, "")))) | ... CM23: =IF(CM$16="","",IF(CM$16=('Model_Assumptions'!$B$8+1), CM$17*$E$13,IF(CM$16<='Model_Assumptions'!$C$8,CM$17*$C$13,IF(CM$16>=('Model_Assumptions'!$C$8 + 1), CM$17*$D$13, ""))))
B25: Free Cash Flow (FCF) | D25: =IF(D16="", "", D19+D21-D22-D23) | E25: =IF(E16="", "", E19+E21-E22-E23) | F25: =IF(F16="", "", F19+F21-F22-F23) | G25: =IF(G16="", "", G19+G21-G22-G23) | H25: =IF(H16="", "", H19+H21-H22-H23) | I25: =IF(I16="", "", I19+I21-I22-I23) | J25: =IF(J16="", "", J19+J21-J22-J23) | K25: =IF(K16="", "", K19+K21-K22-K23) | ... CM25: =IF(CM16="", "", CM19+CM21-CM22-CM23)
B26: Present Value of FCF | D26: =IF(OR(D16="", D$15=$E$7),"",PV($G$43,D$16,0,-D$25)) | E26: =IF(OR(E16="", E$15=$E$7),"",PV($G$43,E$16,0,-E$25)) | F26: =IF(OR(F16="", F$15=$E$7),"",PV($G$43,F$16,0,-F$25)) | G26: =IF(OR(G16="", G$15=$E$7),"",PV($G$43,G$16,0,-G$25)) | H26: =IF(OR(H16="", H$15=$E$7),"",PV($G$43,H$16,0,-H$25)) | I26: =IF(OR(I16="", I$15=$E$7),"",PV($G$43,I$16,0,-I$25)) | J26: =IF(OR(J16="", J$15=$E$7),"",PV($G$43,J$16,0,-J$25)) | K26: =IF(OR(K16="", K$15=$E$7),"",PV($G$43,K$16,0,-K$25)) | ... CM26: =IF(OR(CM16="", CM$15=$E$7),"",PV($G$43,CM$16,0,-CM$25))
B28: DCF | F28: WACC
B29: Net Present Value of FCF | C29: =SUM(OFFSET(D26,0,0,1,('Model_Assumptions'!B8))) | F29: Total Debt | G29: 111302400000
B30: Terminal Value | C30: =INDEX(B15:BI25,11,'Model_Assumptions'!B8+3)/($G$43-'Model_Assumptions'!$E$8) | F30: Current Share Price | G30: 250.12
B31: Present Value of Terminal Value | C31: =PV(H43, 'Model_Assumptions'!$B$8+1, 0, -$C$30) | F31: Weighted Average Shares Outstanding | G31: 15004697000
B32: Enterprise Value | C32: =$C$31 + $C$29 | F32: Market Value of Equity | G32: =$G$30*$G$31
F33: Weight of Equity | G33: =$G$32/($G$29+$G$32)
B34: + Excess Cash | C34: 0 | F34: Weight of Debt | G34: =$G$29/($G$29+$G$32)
B35: - Total Debt | C35: 111302400000
F36: Beta | G36: 0.01
B37: Present Value of Future Equity | C37: =$C$32+$C$34-$C$35 | F37: Risk Free Rate of Return | G37: =Model_Assumptions!$G$8
B38: Weighted Average Shares Outstanding | C38: 15004697000 | F38: Expected Market Return | G38: =Model_Assumptions!$F$8
F39: Market Risk Premium | G39: =$G$38-$G$37
B40: Expected Price Per Share | C40: =$C$37/$C$38 | F40: Expected Return of Equity | G40: =$G$38+($G$39*$G$36)
F41: Expected Cost of Debt | G41: 0.017600699
B42: Under / Over | C42: =IF((C40-G30)/G30 > 0.1, "UNDER VALUED", IF((C40-G30)/G30 < -0.1, "OVER VALUED", "FAIRLY VALUED"))
F43: WACC | G43: =($G$40*$G$33)+($G$41 * $G$34 * (1-$C$9))

Sheet AAPL_Recent_DCF
B3: Recent Evaluation
B6: Evaluation Assumptions
B7: Metric | C7: Rapid Growth Period | D7: Forecast Period | E7: Terminal Period
B8: Sales Growth | C8: ='Model_Assumptions'!C26 | D8: ='Model_Assumptions'!D26 | E8: ='Model_Assumptions'!E26
B9: Effective Tax Rate | C9: ='Model_Assumptions'!C27 | D9: ='Model_Assumptions'!D27 | E9: ='Model_Assumptions'!E27
B10: EBITDA : Revenue (%) | C10: ='Model_Assumptions'!C28 | D10: ='Model_Assumptions'!D28 | E10: ='Model_Assumptions'!E28
B11: Depreciaiton : Revenue (%) | C11: ='Model_Assumptions'!C29 | D11: ='Model_Assumptions'!D29 | E11: ='Model_Assumptions'!E29
B12: Working Capital : Revenue (%) | C12: ='Model_Assumptions'!C30 | D12: ='Model_Assumptions'!D30 | E12: ='Model_Assumptions'!E30
B13: CAPEX : Revenue (%) | C13: ='Model_Assumptions'!C31 | D13: ='Model_Assumptions'!D31 | E13: ='Model_Assumptions'!E31
B15: Cash Flows | D15: =IF(Model_Assumptions!$C$8 = 0, $D$7, $C$7) | E15: =IF(E16=Model_Assumptions!$C$8 +1, $D$7, IF(E16 = Model_Assumptions!$B$8+1, $E$7, "")) | F15: =IF(F16=Model_Assumptions!$C$8 +1, $D$7, IF(F16 = Model_Assumptions!$B$8+1, $E$7, "")) | G15: =IF(G16=Model_Assumptions!$C$8 +1, $D$7, IF(G16 = Model_Assumptions!$B$8+1, $E$7, "")) | H15: =IF(H16=Model_Assumptions!$C$8 +1, $D$7, IF(H16 = Model_Assumptions!$B$8+1, $E$7, "")) | I15: =IF(I16=Model_Assumptions!$C$8 +1, $D$7, IF(I16 = Model_Assumptions!$B$8+1, $E$7, "")) | J15: =IF(J16=Model_Assumptions!$C$8 +1, $D$7, IF(J16 = Model_Assumptions!$B$8+1, $E$7, "")) | K15: =IF(K16=Model_Assumptions!$C$8 +1, $D$7, IF(K16 = Model_Assumptions!$B$8+1, $E$7, "")) | L15: =IF(L16=Model_Assumptions!$C$8 +1, $D$7, IF(L16 = Model_Assumptions!$B$8+1, $E$7, "")) | ... CM15: =IF(CM16=Model_Assumptions!$C$8 +1, $D$7, IF(CM16 = Model_Assumptions!$B$8+1, $E$7, ""))
B16: Year | C16: =0 | D16: =IF(C16<'Model_Assumptions'!$B$8+1,C16+1, "") | E16: =IF(D16<'Model_Assumptions'!$B$8+1,D16+1, "") | F16: =IF(E16<'Model_Assumptions'!$B$8+1,E16+1, "") | G16: =IF(F16<'Model_Assumptions'!$B$8+1,F16+1, "") | H16: =IF(G16<'Model_Assumptions'!$B$8+1,G16+1, "") | I16: =IF(H16<'Model_Assumptions'!$B$8+1,H16+1, "") | J16: =IF(I16<'Model_Assumptions'!$B$8+1,I16+1, "") | K16: =IF(J16<'Model_Assumptions'!$B$8+1,J16+1, "") | ... CM16: =IF(CL16<'Model_Assumptions'!$B$8+1,CL16+1, "")
B17: Revenue | C17: 416161000000 | D17: =IF(D$16="","",IF(D$16=('Model_Assumptions'!$B$8 +1),C$17*(1+$E$8),IF(D$16<='Model_Assumptions'!$C$8,C$17*(1+$C$8),IF(D$16>=('Model_Assumptions'!$C$8+1),C$17*(1+$D$8),"")))) | E17: =IF(E$16="","",IF(E$16=('Model_Assumptions'!$B$8 +1),D$17*(1+$E$8),IF(E$16<='Model_Assumptions'!$C$8,D$17*(1+$C$8),IF(E$16>=('Model_Assumptions'!$C$8+1),D$17*(1+$D$8),"")))) | F17: =IF(F$16="","",IF(F$16=('Model_Assumptions'!$B$8 +1),E$17*(1+$E$8),IF(F$16<='Model_Assumptions'!$C$8,E$17*(1+$C$8),IF(F$16>=('Model_Assumptions'!$C$8+1),E$17*(1+$D$8),"")))) | G17: =IF(G$16="","",IF(G$16=('Model_Assumptions'!$B$8 +1),F$17*(1+$E$8),IF(G$16<='Model_Assumptions'!$C$8,F$17*(1+$C$8),IF(G$16>=('Model_Assumptions'!$C$8+1),F$17*(1+$D$8),"")))) | H17: =IF(H$16="","",IF(H$16=('Model_Assumptions'!$B$8 +1),G$17*(1+$E$8),IF(H$16<='Model_Assumptions'!$C$8,G$17*(1+$C$8),IF(H$16>=('Model_Assumptions'!$C$8+1),G$17*(1+$D$8),"")))) | I17: =IF(I$16="","",IF(I$16=('Model_Assumptions'!$B$8 +1),H$17*(1+$E$8),IF(I$16<='Model_Assumptions'!$C$8,H$17*(1+$C$8),IF(I$16>=('Model_Assumptions'!$C$8+1),H$17*(1+$D$8),"")))) | J17: =IF(J$16="","",IF(J$16=('Model_Assumptions'!$B$8 +1),I$17*(1+$E$8),IF(J$16<='Model_Assumptions'!$C$8,I$17*(1+$C$8),IF(J$16>=('Model_Assumptions'!$C$8+1),I$17*(1+$D$8),"")))) | K17: =IF(K$16="","",IF(K$16=('Model_Assumptions'!$B$8 +1),J$17*(1+$E$8),IF(K$16<='Model_Assumptions'!$C$8,J$17*(1+$C$8),IF(K$16>=('Model_Assumptions'!$C$8+1),J$17*(1+$D$8),"")))) | ... CM17: =IF(CM$16="","",IF(CM$16=('Model_Assumptions'!$B$8 +1),CL$17*(1+$E$8),IF(CM$16<='Model_Assumptions'!$C$8,CL$17*(1+$C$8),IF(CM$16>=('Model_Assumptions'!$C$8+1),CL$17*(1+$D$8),""))))
B18: EBITDA | D18: =IF(D$16="","",IF(D$16=('Model_Assumptions'!$B$8+1), D$17*$E$10,IF(D$16<='Model_Assumptions'!$C$8,D$17*$C$10,IF(D$16>=('Model_Assumptions'!$C$8 + 1), D$17*$D$10, "")))) | E18: =IF(E$16="","",IF(E$16=('Model_Assumptions'!$B$8+1), E$17*$E$10,IF(E$16<='Model_Assumptions'!$C$8,E$17*$C$10,IF(E$16>=('Model_Assumptions'!$C$8 + 1), E$17*$D$10, "")))) | F18: =IF(F$16="","",IF(F$16=('Model_Assumptions'!$B$8+1), F$17*$E$10,IF(F$16<='Model_Assumptions'!$C$8,F$17*$C$10,IF(F$16>=('Model_Assumptions'!$C$8 + 1), F$17*$D$10, "")))) | G18: =IF(G$16="","",IF(G$16=('Model_Assumptions'!$B$8+1), G$17*$E$10,IF(G$16<='Model_Assumptions'!$C$8,G$17*$C$10,IF(G$16>=('Model_Assumptions'!$C$8 + 1), G$17*$D$10, "")))) | H18: =IF(H$16="","",IF(H$16=('Model_Assumptions'!$B$8+1), H$17*$E$10,IF(H$16<='Model_Assumptions'!$C$8,H$17*$C$10,IF(H$16>=('Model_Assumptions'!$C$8 + 1), H$17*$D$10, "")))) | I18: =IF(I$16="","",IF(I$16=('Model_Assumptions'!$B$8+1), I$17*$E$10,IF(I$16<='Model_Assumptions'!$C$8,I$17*$C$10,IF(I$16>=('Model_Assumptions'!$C$8 + 1), I$17*$D$10, "")))) | J18: =IF(J$16="","",IF(J$16=('Model_Assumptions'!$B$8+1), J$17*$E$10,IF(J$16<='Model_Assumptions'!$C$8,J$17*$C$10,IF(J$16>=('Model_Assumptions'!$C$8 + 1), J$17*$D$10, "")))) | K18: =IF(K$16="","",IF(K$16=('Model_Assumptions'!$B$8+1), K$17*$E$10,IF(K$16<='Model_Assumptions'!$C$8,K$17*$C$10,IF(K$16>=('Model_Assumptions'!$C$8 + 1), K$17*$D$10, "")))) | ... CM18: =IF(CM$16="","",IF(CM$16=('Model_Assumptions'!$B$8+1), CM$17*$E$10,IF(CM$16<='Model_Assumptions'!$C$8,CM$17*$C$10,IF(CM$16>=('Model_Assumptions'!$C$8 + 1), CM$17*$D$10, ""))))
B19: EBITDA After Tax | D19: =IF(D$16="","", IF(D$16=('Model_Assumptions'!$B$8+1), D$18*(1-$E$9),IF(D$16<='Model_Assumptions'!$C$8,D$18*(1-$C$9),IF(D$16>=('Model_Assumptions'!$C$8 + 1), D$18*(1-$D$9), "")))) | E19: =IF(E$16="","", IF(E$16=('Model_Assumptions'!$B$8+1), E$18*(1-$E$9),IF(E$16<='Model_Assumptions'!$C$8,E$18*(1-$C$9),IF(E$16>=('Model_Assumptions'!$C$8 + 1), E$18*(1-$D$9), "")))) | F19: =IF(F$16="","", IF(F$16=('Model_Assumptions'!$B$8+1), F$18*(1-$E$9),IF(F$16<='Model_Assumptions'!$C$8,F$18*(1-$C$9),IF(F$16>=('Model_Assumptions'!$C$8 + 1), F$18*(1-$D$9), "")))) | G19: =IF(G$16="","", IF(G$16=('Model_Assumptions'!$B$8+1), G$18*(1-$E$9),IF(G$16<='Model_Assumptions'!$C$8,G$18*(1-$C$9),IF(G$16>=('Model_Assumptions'!$C$8 + 1), G$18*(1-$D$9), "")))) | H19: =IF(H$16="","", IF(H$16=('Model_Assumptions'!$B$8+1), H$18*(1-$E$9),IF(H$16<='Model_Assumptions'!$C$8,H$18*(1-$C$9),IF(H$16>=('Model_Assumptions'!$C$8 + 1), H$18*(1-$D$9), "")))) | I19: =IF(I$16="","", IF(I$16=('Model_Assumptions'!$B$8+1), I$18*(1-$E$9),IF(I$16<='Model_Assumptions'!$C$8,I$18*(1-$C$9),IF(I$16>=('Model_Assumptions'!$C$8 + 1), I$18*(1-$D$9), "")))) | J19: =IF(J$16="","", IF(J$16=('Model_Assumptions'!$B$8+1), J$18*(1-$E$9),IF(J$16<='Model_Assumptions'!$C$8,J$18*(1-$C$9),IF(J$16>=('Model_Assumptions'!$C$8 + 1), J$18*(1-$D$9), "")))) | K19: =IF(K$16="","", IF(K$16=('Model_Assumptions'!$B$8+1), K$18*(1-$E$9),IF(K$16<='Model_Assumptions'!$C$8,K$18*(1-$C$9),IF(K$16>=('Model_Assumptions'!$C$8 + 1), K$18*(1-$D$9), "")))) | ... CM19: =IF(CM$16="","", IF(CM$16=('Model_Assumptions'!$B$8+1), CM$18*(1-$E$9),IF(CM$16<='Model_Assumptions'!$C$8,CM$18*(1-$C$9),IF(CM$16>=('Model_Assumptions'!$C$8 + 1), CM$18*(1-$D$9), ""))))
B20: Depreciation | D20: =IF(D$16="","",IF(D$16=('Model_Assumptions'!$B$8+1), D$17*$E$11,IF(D$16<='Model_Assumptions'!$C$8,D$17*$C$11,IF(D$16>=('Model_Assumptions'!$C$8 + 1), D$17*$D$11, "")))) | E20: =IF(E$16="","",IF(E$16=('Model_Assumptions'!$B$8+1), E$17*$E$11,IF(E$16<='Model_Assumptions'!$C$8,E$17*$C$11,IF(E$16>=('Model_Assumptions'!$C$8 + 1), E$17*$D$11, "")))) | F20: =IF(F$16="","",IF(F$16=('Model_Assumptions'!$B$8+1), F$17*$E$11,IF(F$16<='Model_Assumptions'!$C$8,F$17*$C$11,IF(F$16>=('Model_Assumptions'!$C$8 + 1), F$17*$D$11, "")))) | G20: =IF(G$16="","",IF(G$16=('Model_Assumptions'!$B$8+1), G$17*$E$11,IF(G$16<='Model_Assumptions'!$C$8,G$17*$C$11,IF(G$16>=('Model_Assumptions'!$C$8 + 1), G$17*$D$11, "")))) | H20: =IF(H$16="","",IF(H$16=('Model_Assumptions'!$B$8+1), H$17*$E$11,IF(H$16<='Model_Assumptions'!$C$8,H$17*$C$11,IF(H$16>=('Model_Assumptions'!$C$8 + 1), H$17*$D$11, "")))) | I20: =IF(I$16="","",IF(I$16=('Model_Assumptions'!$B$8+1), I$17*$E$11,IF(I$16<='Model_Assumptions'!$C$8,I$17*$C$11,IF(I$16>=('Model_Assumptions'!$C$8 + 1), I$17*$D$11, "")))) | J20: =IF(J$16="","",IF(J$16=('Model_Assumptions'!$B$8+1), J$17*$E$11,IF(J$16<='Model_Assumptions'!$C$8,J$17*$C$11,IF(J$16>=('Model_Assumptions'!$C$8 + 1), J$17*$D$11, "")))) | K20: =IF(K$16="","",IF(K$16=('Model_Assumptions'!$B$8+1), K$17*$E$11,IF(K$16<='Model_Assumptions'!$C$8,K$17*$C$11,IF(K$16>=('Model_Assumptions'!$C$8 + 1), K$17*$D$11, "")))) | ... CM20: =IF(CM$16="","",IF(CM$16=('Model_Assumptions'!$B$8+1), CM$17*$E$11,IF(CM$16<='Model_Assumptions'!$C$8,CM$17*$C$11,IF(CM$16>=('Model_Assumptions'!$C$8 + 1), CM$17*$D$11, ""))))
B21: Depreciation Tax Shield | D21: =IF(D$16 = "","", IF(D$16 =( 'Model_Assumptions'!$B$8 +1), D$20 * $E$9, IF(D$16 <= 'Model_Assumptions'!$C$8, D$20 * $C$9, IF(D$16 >= ('Model_Assumptions'!$C$8 + 1), D$20 * $D$9)))) | E21: =IF(E$16 = "","", IF(E$16 =( 'Model_Assumptions'!$B$8 +1), E$20 * $E$9, IF(E$16 <= 'Model_Assumptions'!$C$8, E$20 * $C$9, IF(E$16 >= ('Model_Assumptions'!$C$8 + 1), E$20 * $D$9)))) | F21: =IF(F$16 = "","", IF(F$16 =( 'Model_Assumptions'!$B$8 +1), F$20 * $E$9, IF(F$16 <= 'Model_Assumptions'!$C$8, F$20 * $C$9, IF(F$16 >= ('Model_Assumptions'!$C$8 + 1), F$20 * $D$9)))) | G21: =IF(G$16 = "","", IF(G$16 =( 'Model_Assumptions'!$B$8 +1), G$20 * $E$9, IF(G$16 <= 'Model_Assumptions'!$C$8, G$20 * $C$9, IF(G$16 >= ('Model_Assumptions'!$C$8 + 1), G$20 * $D$9)))) | H21: =IF(H$16 = "","", IF(H$16 =( 'Model_Assumptions'!$B$8 +1), H$20 * $E$9, IF(H$16 <= 'Model_Assumptions'!$C$8, H$20 * $C$9, IF(H$16 >= ('Model_Assumptions'!$C$8 + 1), H$20 * $D$9)))) | I21: =IF(I$16 = "","", IF(I$16 =( 'Model_Assumptions'!$B$8 +1), I$20 * $E$9, IF(I$16 <= 'Model_Assumptions'!$C$8, I$20 * $C$9, IF(I$16 >= ('Model_Assumptions'!$C$8 + 1), I$20 * $D$9)))) | J21: =IF(J$16 = "","", IF(J$16 =( 'Model_Assumptions'!$B$8 +1), J$20 * $E$9, IF(J$16 <= 'Model_Assumptions'!$C$8, J$20 * $C$9, IF(J$16 >= ('Model_Assumptions'!$C$8 + 1), J$20 * $D$9)))) | K21: =IF(K$16 = "","", IF(K$16 =( 'Model_Assumptions'!$B$8 +1), K$20 * $E$9, IF(K$16 <= 'Model_Assumptions'!$C$8, K$20 * $C$9, IF(K$16 >= ('Model_Assumptions'!$C$8 + 1), K$20 * $D$9)))) | ... CM21: =IF(CM$16 = "","", IF(CM$16 =( 'Model_Assumptions'!$B$8 +1), CM$20 * $E$9, IF(CM$16 <= 'Model_Assumptions'!$C$8, CM$20 * $C$9, IF(CM$16 >= ('Model_Assumptions'!$C$8 + 1), CM$20 * $D$9))))
B22: Change in Working Capital | D22: =IF(D$16="","",IF(D$16=('Model_Assumptions'!$B$8+1),( D$17-C$17)*$E$12,IF(D$16<='Model_Assumptions'!$C$8,( D$17-C$17)*$C$12,IF(D$16>=('Model_Assumptions'!$C$8 + 1), ( D$17-C$17)*$D$12, "")))) | E22: =IF(E$16="","",IF(E$16=('Model_Assumptions'!$B$8+1),( E$17-D$17)*$E$12,IF(E$16<='Model_Assumptions'!$C$8,( E$17-D$17)*$C$12,IF(E$16>=('Model_Assumptions'!$C$8 + 1), ( E$17-D$17)*$D$12, "")))) | F22: =IF(F$16="","",IF(F$16=('Model_Assumptions'!$B$8+1),( F$17-E$17)*$E$12,IF(F$16<='Model_Assumptions'!$C$8,( F$17-E$17)*$C$12,IF(F$16>=('Model_Assumptions'!$C$8 + 1), ( F$17-E$17)*$D$12, "")))) | G22: =IF(G$16="","",IF(G$16=('Model_Assumptions'!$B$8+1),( G$17-F$17)*$E$12,IF(G$16<='Model_Assumptions'!$C$8,( G$17-F$17)*$C$12,IF(G$16>=('Model_Assumptions'!$C$8 + 1), ( G$17-F$17)*$D$12, "")))) | H22: =IF(H$16="","",IF(H$16=('Model_Assumptions'!$B$8+1),( H$17-G$17)*$E$12,IF(H$16<='Model_Assumptions'!$C$8,( H$17-G$17)*$C$12,IF(H$16>=('Model_Assumptions'!$C$8 + 1), ( H$17-G$17)*$D$12, "")))) | I22: =IF(I$16="","",IF(I$16=('Model_Assumptions'!$B$8+1),( I$17-H$17)*$E$12,IF(I$16<='Model_Assumptions'!$C$8,( I$17-H$17)*$C$12,IF(I$16>=('Model_Assumptions'!$C$8 + 1), ( I$17-H$17)*$D$12, "")))) | J22: =IF(J$16="","",IF(J$16=('Model_Assumptions'!$B$8+1),( J$17-I$17)*$E$12,IF(J$16<='Model_Assumptions'!$C$8,( J$17-I$17)*$C$12,IF(J$16>=('Model_Assumptions'!$C$8 + 1), ( J$17-I$17)*$D$12, "")))) | K22: =IF(K$16="","",IF(K$16=('Model_Assumptions'!$B$8+1),( K$17-J$17)*$E$12,IF(K$16<='Model_Assumptions'!$C$8,( K$17-J$17)*$C$12,IF(K$16>=('Model_Assumptions'!$C$8 + 1), ( K$17-J$17)*$D$12, "")))) | ... CM22: =IF(CM$16="","",IF(CM$16=('Model_Assumptions'!$B$8+1),( CM$17-CL$17)*$E$12,IF(CM$16<='Model_Assumptions'!$C$8,( CM$17-CL$17)*$C$12,IF(CM$16>=('Model_Assumptions'!$C$8 + 1), ( CM$17-CL$17)*$D$12, ""))))
B23: Capital Expenditures | D23: =IF(D$16="","",IF(D$16=('Model_Assumptions'!$B$8+1), D$17*$E$13,IF(D$16<='Model_Assumptions'!$C$8,D$17*$C$13,IF(D$16>=('Model_Assumptions'!$C$8 + 1), D$17*$D$13, "")))) | E23: =IF(E$16="","",IF(E$16=('Model_Assumptions'!$B$8+1), E$17*$E$13,IF(E$16<='Model_Assumptions'!$C$8,E$17*$C$13,IF(E$16>=('Model_Assumptions'!$C$8 + 1), E$17*$D$13, "")))) | F23: =IF(F$16="","",IF(F$16=('Model_Assumptions'!$B$8+1), F$17*$E$13,IF(F$16<='Model_Assumptions'!$C$8,F$17*$C$13,IF(F$16>=('Model_Assumptions'!$C$8 + 1), F$17*$D$13, "")))) | G23: =IF(G$16="","",IF(G$16=('Model_Assumptions'!$B$8+1), G$17*$E$13,IF(G$16<='Model_Assumptions'!$C$8,G$17*$C$13,IF(G$16>=('Model_Assumptions'!$C$8 + 1), G$17*$D$13, "")))) | H23: =IF(H$16="","",IF(H$16=('Model_Assumptions'!$B$8+1), H$17*$E$13,IF(H$16<='Model_Assumptions'!$C$8,H$17*$C$13,IF(H$16>=('Model_Assumptions'!$C$8 + 1), H$17*$D$13, "")))) | I23: =IF(I$16="","",IF(I$16=('Model_Assumptions'!$B$8+1), I$17*$E$13,IF(I$16<='Model_Assumptions'!$C$8,I$17*$C$13,IF(I$16>=('Model_Assumptions'!$C$8 + 1), I$17*$D$13, "")))) | J23: =IF(J$16="","",IF(J$16=('Model_Assumptions'!$B$8+1), J$17*$E$13,IF(J$16<='Model_Assumptions'!$C$8,J$17*$C$13,IF(J$16>=('Model_Assumptions'!$C$8 + 1), J$17*$D$13, "")))) | K23: =IF(K$16="","",IF(K$16=('Model_Assumptions'!$B$8+1), K$17*$E$13,IF(K$16<='Model_Assumptions'!$C$8,K$17*$C$13,IF(K$16>=('Model_Assumptions'!$C$8 + 1), K$17*$D$13, "")))) | ... CM23: =IF(CM$16="","",IF(CM$16=('Model_Assumptions'!$B$8+1), CM$17*$E$13,IF(CM$16<='Model_Assumptions'!$C$8,CM$17*$C$13,IF(CM$16>=('Model_Assumptions'!$C$8 + 1), CM$17*$D$13, ""))))
B25: Free Cash Flow (FCF) | D25: =IF(D16="", "", D19+D21-D22-D23) | E25: =IF(E16="", "", E19+E21-E22-E23) | F25: =IF(F16="", "", F19+F21-F22-F23) | G25: =IF(G16="", "", G19+G21-G22-G23) | H25: =IF(H16="", "", H19+H21-H22-H23) | I25: =IF(I16="", "", I19+I21-I22-I23) | J25: =IF(J16="", "", J19+J21-J22-J23) | K25: =IF(K16="", "", K19+K21-K22-K23) | ... CM25: =IF(CM16="", "", CM19+CM21-CM22-CM23)
B26: Present Value of FCF | D26: =IF(OR(D16="", D$15=$E$7),"",PV($G$43,D$16,0,-D$25)) | E26: =IF(OR(E16="", E$15=$E$7),"",PV($G$43,E$16,0,-E$25)) | F26: =IF(OR(F16="", F$15=$E$7),"",PV($G$43,F$16,0,-F$25)) | G26: =IF(OR(G16="", G$15=$E$7),"",PV($G$43,G$16,0,-G$25)) | H26: =IF(OR(H16="", H$15=$E$7),"",PV($G$43,H$16,0,-H$25)) | I26: =IF(OR(I16="", I$15=$E$7),"",PV($G$43,I$16,0,-I$25)) | J26: =IF(OR(J16="", J$15=$E$7),"",PV($G$43,J$16,0,-J$25)) | K26: =IF(OR(K16="", K$15=$E$7),"",PV($G$43,K$16,0,-K$25)) | ... CM26: =IF(OR(CM16="", CM$15=$E$7),"",PV($G$43,CM$16,0,-CM$25))
B28: DCF | F28: WACC
B29: Net Present Value of FCF | C29: =SUM(OFFSET(D26,0,0,1,('Model_Assumptions'!B8))) | F29: Total Debt | G29: 98657000000
B30: Terminal Value | C30: =INDEX(B15:BI25,11,'Model_Assumptions'!B8+3)/($G$43-'Model_Assumptions'!$E$8) | F30: Current Share Price | G30: 250.12
B31: Present Value of Terminal Value | C31: =PV(H43, 'Model_Assumptions'!$B$8+1, 0, -$C$30) | F31: Weighted Average Shares Outstanding | G31: 15004697000
B32: Enterprise Value | C32: =$C$31 + $C$29 | F32: Market Value of Equity | G32: =$G$30*$G$31
F33: Weight of Equity | G33: =$G$32/($G$29+$G$32)
B34: + Excess Cash | C34: 0 | F34: Weight of Debt | G34: =$G$29/($G$29+$G$32)
B35: - Total Debt | C35: 98657000000
F36: Beta | G36: 0.01
B37: Present Value of Future Equity | C37: =$C$32+$C$34-$C$35 | F37: Risk Free Rate of Return | G37: =Model_Assumptions!$G$8
B38: Weighted Average Shares Outstanding | C38: 15004697000 | F38: Expected Market Return | G38: =Model_Assumptions!$F$8
F39: Market Risk Premium | G39: =$G$38-$G$37
B40: Expected Price Per Share | C40: =$C$37/$C$38 | F40: Expected Return of Equity | G40: =$G$38+($G$39*$G$36)
F41: Expected Cost of Debt | G41: 0
B42: Under / Over | C42: =IF((C40-G30)/G30 > 0.1, "UNDER VALUED", IF((C40-G30)/G30 < -0.1, "OVER VALUED", "FAIRLY VALUED"))
F43: WACC | G43: =($G$40*$G$33)+($G$41 * $G$34 * (1-$C$9))

Sheet AAPL_Custom_DCF
B3: Custom Evaluation
B6: Evaluation Assumptions
B7: Metric | C7: Rapid Growth Period | D7: Forecast Period | E7: Terminal Period
B8: Sales Growth | C8: ='Model_Assumptions'!C13 | D8: ='Model_Assumptions'!D13 | E8: ='Model_Assumptions'!E13
B9: Effective Tax Rate | C9: ='Model_Assumptions'!C14 | D9: ='Model_Assumptions'!D14 | E9: ='Model_Assumptions'!E14
B10: EBITDA : Revenue (%) | C10: ='Model_Assumptions'!C15 | D10: ='Model_Assumptions'!D15 | E10: ='Model_Assumptions'!E15
B11: Depreciaiton : Revenue (%) | C11: ='Model_Assumptions'!C16 | D11: ='Model_Assumptions'!D16 | E11: ='Model_Assumptions'!E16
B12: Working Capital : Revenue (%) | C12: ='Model_Assumptions'!C17 | D12: ='Model_Assumptions'!D17 | E12: ='Model_Assumptions'!E17
B13: CAPEX : Revenue (%) | C13: ='Model_Assumptions'!C18 | D13: ='Model_Assumptions'!D18 | E13: ='Model_Assumptions'!E18
B15: Cash Flows | D15: =IF(Model_Assumptions!$C$8 = 0, $D$7, $C$7) | E15: =IF(E16=Model_Assumptions!$C$8 +1, $D$7, IF(E16 = Model_Assumptions!$B$8+1, $E$7, "")) | F15: =IF(F16=Model_Assumptions!$C$8 +1, $D$7, IF(F16 = Model_Assumptions!$B$8+1, $E$7, "")) | G15: =IF(G16=Model_Assumptions!$C$8 +1, $D$7, IF(G16 = Model_Assumptions!$B$8+1, $E$7, "")) | H15: =IF(H16=Model_Assumptions!$C$8 +1, $D$7, IF(H16 = Model_Assumptions!$B$8+1, $E$7, "")) | I15: =IF(I16=Model_Assumptions!$C$8 +1, $D$7, IF(I16 = Model_Assumptions!$B$8+1, $E$7, "")) | J15: =IF(J16=Model_Assumptions!$C$8 +1, $D$7, IF(J16 = Model_Assumptions!$B$8+1, $E$7, "")) | K15: =IF(K16=Model_Assumptions!$C$8 +1, $D$7, IF(K16 = Model_Assumptions!$B$8+1, $E$7, "")) | L15: =IF(L16=Model_Assumptions!$C$8 +1, $D$7, IF(L16 = Model_Assumptions!$B$8+1, $E$7, "")) | ... CM15: =IF(CM16=Model_Assumptions!$C$8 +1, $D$7, IF(CM16 = Model_Assumptions!$B$8+1, $E$7, ""))
B16: Year | C16: =0 | D16: =IF(C16<'Model_Assumptions'!$B$8+1,C16+1, "") | E16: =IF(D16<'Model_Assumptions'!$B$8+1,D16+1, "") | F16: =IF(E16<'Model_Assumptions'!$B$8+1,E16+1, "") | G16: =IF(F16<'Model_Assumptions'!$B$8+1,F16+1, "") | H16: =IF(G16<'Model_Assumptions'!$B$8+1,G16+1, "") | I16: =IF(H16<'Model_Assumptions'!$B$8+1,H16+1, "") | J16: =IF(I16<'Model_Assumptions'!$B$8+1,I16+1, "") | K16: =IF(J16<'Model_Assumptions'!$B$8+1,J16+1, "") | ... CM16: =IF(CL16<'Model_Assumptions'!$B$8+1,CL16+1, "")
B17: Revenue | C17: 416161000000 | D17: =IF(D$16="","",IF(D$16=('Model_Assumptions'!$B$8 +1),C$17*(1+$E$8),IF(D$16<='Model_Assumptions'!$C$8,C$17*(1+$C$8),IF(D$16>=('Model_Assumptions'!$C$8+1),C$17*(1+$D$8),"")))) | E17: =IF(E$16="","",IF(E$16=('Model_Assumptions'!$B$8 +1),D$17*(1+$E$8),IF(E$16<='Model_Assumptions'!$C$8,D$17*(1+$C$8),IF(E$16>=('Model_Assumptions'!$C$8+1),D$17*(1+$D$8),"")))) | F17: =IF(F$16="","",IF(F$16=('Model_Assumptions'!$B$8 +1),E$17*(1+$E$8),IF(F$16<='Model_Assumptions'!$C$8,E$17*(1+$C$8),IF(F$16>=('Model_Assumptions'!$C$8+1),E$17*(1+$D$8),"")))) | G17: =IF(G$16="","",IF(G$16=('Model_Assumptions'!$B$8 +1),F$17*(1+$E$8),IF(G$16<='Model_Assumptions'!$C$8,F$17*(1+$C$8),IF(G$16>=('Model_Assumptions'!$C$8+1),F$17*(1+$D$8),"")))) | H17: =IF(H$16="","",IF(H$16=('Model_Assumptions'!$B$8 +1),G$17*(1+$E$8),IF(H$16<='Model_Assumptions'!$C$8,G$17*(1+$C$8),IF(H$16>=('Model_Assumptions'!$C$8+1),G$17*(1+$D$8),"")))) | I17: =IF(I$16="","",IF(I$16=('Model_Assumptions'!$B$8 +1),H$17*(1+$E$8),IF(I$16<='Model_Assumptions'!$C$8,H$17*(1+$C$8),IF(I$16>=('Model_Assumptions'!$C$8+1),H$17*(1+$D$8),"")))) | J17: =IF(J$16="","",IF(J$16=('Model_Assumptions'!$B$8 +1),I$17*(1+$E$8),IF(J$16<='Model_Assumptions'!$C$8,I$17*(1+$C$8),IF(J$16>=('Model_Assumptions'!$C$8+1),I$17*(1+$D$8),"")))) | K17: =IF(K$16="","",IF(K$16=('Model_Assumptions'!$B$8 +1),J$17*(1+$E$8),IF(K$16<='Model_Assumptions'!$C$8,J$17*(1+$C$8),IF(K$16>=('Model_Assumptions'!$C$8+1),J$17*(1+$D$8),"")))) | ... CM17: =IF(CM$16="","",IF(CM$16=('Model_Assumptions'!$B$8 +1),CL$17*(1+$E$8),IF(CM$16<='Model_Assumptions'!$C$8,CL$17*(1+$C$8),IF(CM$16>=('Model_Assumptions'!$C$8+1),CL$17*(1+$D$8),""))))
B18: EBITDA | D18: =IF(D$16="","",IF(D$16=('Model_Assumptions'!$B$8+1), D$17*$E$10,IF(D$16<='Model_Assumptions'!$C$8,D$17*$C$10,IF(D$16>=('Model_Assumptions'!$C$8 + 1), D$17*$D$10, "")))) | E18: =IF(E$16="","",IF(E$16=('Model_Assumptions'!$B$8+1), E$17*$E$10,IF(E$16<='Model_Assumptions'!$C$8,E$17*$C$10,IF(E$16>=('Model_Assumptions'!$C$8 + 1), E$17*$D$10, "")))) | F18: =IF(F$16="","",IF(F$16=('Model_Assumptions'!$B$8+1), F$17*$E$10,IF(F$16<='Model_Assumptions'!$C$8,F$17*$C$10,IF(F$16>=('Model_Assumptions'!$C$8 + 1), F$17*$D$10, "")))) | G18: =IF(G$16="","",IF(G$16=('Model_Assumptions'!$B$8+1), G$17*$E$10,IF(G$16<='Model_Assumptions'!$C$8,G$17*$C$10,IF(G$16>=('Model_Assumptions'!$C$8 + 1), G$17*$D$10, "")))) | H18: =IF(H$16="","",IF(H$16=('Model_Assumptions'!$B$8+1), H$17*$E$10,IF(H$16<='Model_Assumptions'!$C$8,H$17*$C$10,IF(H$16>=('Model_Assumptions'!$C$8 + 1), H$17*$D$10, "")))) | I18: =IF(I$16="","",IF(I$16=('Model_Assumptions'!$B$8+1), I$17*$E$10,IF(I$16<='Model_Assumptions'!$C$8,I$17*$C$10,IF(I$16>=('Model_Assumptions'!$C$8 + 1), I$17*$D$10, "")))) | J18: =IF(J$16="","",IF(J$16=('Model_Assumptions'!$B$8+1), J$17*$E$10,IF(J$16<='Model_Assumptions'!$C$8,J$17*$C$10,IF(J$16>=('Model_Assumptions'!$C$8 + 1), J$17*$D$10, "")))) | K18: =IF(K$16="","",IF(K$16=('Model_Assumptions'!$B$8+1), K$17*$E$10,IF(K$16<='Model_Assumptions'!$C$8,K$17*$C$10,IF(K$16>=('Model_Assumptions'!$C$8 + 1), K$17*$D$10, "")))) | ... CM18: =IF(CM$16="","",IF(CM$16=('Model_Assumptions'!$B$8+1), CM$17*$E$10,IF(CM$16<='Model_Assumptions'!$C$8,CM$17*$C$10,IF(CM$16>=('Model_Assumptions'!$C$8 + 1), CM$17*$D$10, ""))))
B19: EBITDA After Tax | D19: =IF(D$16="","", IF(D$16=('Model_Assumptions'!$B$8+1), D$18*(1-$E$9),IF(D$16<='Model_Assumptions'!$C$8,D$18*(1-$C$9),IF(D$16>=('Model_Assumptions'!$C$8 + 1), D$18*(1-$D$9), "")))) | E19: =IF(E$16="","", IF(E$16=('Model_Assumptions'!$B$8+1), E$18*(1-$E$9),IF(E$16<='Model_Assumptions'!$C$8,E$18*(1-$C$9),IF(E$16>=('Model_Assumptions'!$C$8 + 1), E$18*(1-$D$9), "")))) | F19: =IF(F$16="","", IF(F$16=('Model_Assumptions'!$B$8+1), F$18*(1-$E$9),IF(F$16<='Model_Assumptions'!$C$8,F$18*(1-$C$9),IF(F$16>=('Model_Assumptions'!$C$8 + 1), F$18*(1-$D$9), "")))) | G19: =IF(G$16="","", IF(G$16=('Model_Assumptions'!$B$8+1), G$18*(1-$E$9),IF(G$16<='Model_Assumptions'!$C$8,G$18*(1-$C$9),IF(G$16>=('Model_Assumptions'!$C$8 + 1), G$18*(1-$D$9), "")))) | H19: =IF(H$16="","", IF(H$16=('Model_Assumptions'!$B$8+1), H$18*(1-$E$9),IF(H$16<='Model_Assumptions'!$C$8,H$18*(1-$C$9),IF(H$16>=('Model_Assumptions'!$C$8 + 1), H$18*(1-$D$9), "")))) | I19: =IF(I$16="","", IF(I$16=('Model_Assumptions'!$B$8+1), I$18*(1-$E$9),IF(I$16<='Model_Assumptions'!$C$8,I$18*(1-$C$9),IF(I$16>=('Model_Assumptions'!$C$8 + 1), I$18*(1-$D$9), "")))) | J19: =IF(J$16="","", IF(J$16=('Model_Assumptions'!$B$8+1), J$18*(1-$E$9),IF(J$16<='Model_Assumptions'!$C$8,J$18*(1-$C$9),IF(J$16>=('Model_Assumptions'!$C$8 + 1), J$18*(1-$D$9), "")))) | K19: =IF(K$16="","", IF(K$16=('Model_Assumptions'!$B$8+1), K$18*(1-$E$9),IF(K$16<='Model_Assumptions'!$C$8,K$18*(1-$C$9),IF(K$16>=('Model_Assumptions'!$C$8 + 1), K$18*(1-$D$9), "")))) | ... CM19: =IF(CM$16="","", IF(CM$16=('Model_Assumptions'!$B$8+1), CM$18*(1-$E$9),IF(CM$16<='Model_Assumptions'!$C$8,CM$18*(1-$C$9),IF(CM$16>=('Model_Assumptions'!$C$8 + 1), CM$18*(1-$D$9), ""))))
B20: Depreciation | D20: =IF(D$16="","",IF(D$16=('Model_Assumptions'!$B$8+1), D$17*$E$11,IF(D$16<='Model_Assumptions'!$C$8,D$17*$C$11,IF(D$16>=('Model_Assumptions'!$C$8 + 1), D$17*$D$11, "")))) | E20: =IF(E$16="","",IF(E$16=('Model_Assumptions'!$B$8+1), E$17*$E$11,IF(E$16<='Model_Assumptions'!$C$8,E$17*$C$11,IF(E$16>=('Model_Assumptions'!$C$8 + 1), E$17*$D$11, "")))) | F20: =IF(F$16="","",IF(F$16=('Model_Assumptions'!$B$8+1), F$17*$E$11,IF(F$16<='Model_Assumptions'!$C$8,F$17*$C$11,IF(F$16>=('Model_Assumptions'!$C$8 + 1), F$17*$D$11, "")))) | G20: =IF(G$16="","",IF(G$16=('Model_Assumptions'!$B$8+1), G$17*$E$11,IF(G$16<='Model_Assumptions'!$C$8,G$17*$C$11,IF(G$16>=('Model_Assumptions'!$C$8 + 1), G$17*$D$11, "")))) | H20: =IF(H$16="","",IF(H$16=('Model_Assumptions'!$B$8+1), H$17*$E$11,IF(H$16<='Model_Assumptions'!$C$8,H$17*$C$11,IF(H$16>=('Model_Assumptions'!$C$8 + 1), H$17*$D$11, "")))) | I20: =IF(I$16="","",IF(I$16=('Model_Assumptions'!$B$8+1), I$17*$E$11,IF(I$16<='Model_Assumptions'!$C$8,I$17*$C$11,IF(I$16>=('Model_Assumptions'!$C$8 + 1), I$17*$D$11, "")))) | J20: =IF(J$16="","",IF(J$16=('Model_Assumptions'!$B$8+1), J$17*$E$11,IF(J$16<='Model_Assumptions'!$C$8,J$17*$C$11,IF(J$16>=('Model_Assumptions'!$C$8 + 1), J$17*$D$11, "")))) | K20: =IF(K$16="","",IF(K$16=('Model_Assumptions'!$B$8+1), K$17*$E$11,IF(K$16<='Model_Assumptions'!$C$8,K$17*$C$11,IF(K$16>=('Model_Assumptions'!$C$8 + 1), K$17*$D$11, "")))) | ... CM20: =IF(CM$16="","",IF(CM$16=('Model_Assumptions'!$B$8+1), CM$17*$E$11,IF(CM$16<='Model_Assumptions'!$C$8,CM$17*$C$11,IF(CM$16>=('Model_Assumptions'!$C$8 + 1), CM$17*$D$11, ""))))
B21: Depreciation Tax Shield | D21: =IF(D$16 = "","", IF(D$16 =( 'Model_Assumptions'!$B$8 +1), D$20 * $E$9, IF(D$16 <= 'Model_Assumptions'!$C$8, D$20 * $C$9, IF(D$16 >= ('Model_Assumptions'!$C$8 + 1), D$20 * $D$9)))) | E21: =IF(E$16 = "","", IF(E$16 =( 'Model_Assumptions'!$B$8 +1), E$20 * $E$9, IF(E$16 <= 'Model_Assumptions'!$C$8, E$20 * $C$9, IF(E$16 >= ('Model_Assumptions'!$C$8 + 1), E$20 * $D$9)))) | F21: =IF(F$16 = "","", IF(F$16 =( 'Model_Assumptions'!$B$8 +1), F$20 * $E$9, IF(F$16 <= 'Model_Assumptions'!$C$8, F$20 * $C$9, IF(F$16 >= ('Model_Assumptions'!$C$8 + 1), F$20 * $D$9)))) | G21: =IF(G$16 = "","", IF(G$16 =( 'Model_Assumptions'!$B$8 +1), G$20 * $E$9, IF(G$16 <= 'Model_Assumptions'!$C$8, G$20 * $C$9, IF(G$16 >= ('Model_Assumptions'!$C$8 + 1), G$20 * $D$9)))) | H21: =IF(H$16 = "","", IF(H$16 =( 'Model_Assumptions'!$B$8 +1), H$20 * $E$9, IF(H$16 <= 'Model_Assumptions'!$C$8, H$20 * $C$9, IF(H$16 >= ('Model_Assumptions'!$C$8 + 1), H$20 * $D$9)))) | I21: =IF(I$16 = "","", IF(I$16 =( 'Model_Assumptions'!$B$8 +1), I$20 * $E$9, IF(I$16 <= 'Model_Assumptions'!$C$8, I$20 * $C$9, IF(I$16 >= ('Model_Assumptions'!$C$8 + 1), I$20 * $D$9)))) | J21: =IF(J$16 = "","", IF(J$16 =( 'Model_Assumptions'!$B$8 +1), J$20 * $E$9, IF(J$16 <= 'Model_Assumptions'!$C$8, J$20 * $C$9, IF(J$16 >= ('Model_Assumptions'!$C$8 + 1), J$20 * $D$9)))) | K21: =IF(K$16 = "","", IF(K$16 =( 'Model_Assumptions'!$B$8 +1), K$20 * $E$9, IF(K$16 <= 'Model_Assumptions'!$C$8, K$20 * $C$9, IF(K$16 >= ('Model_Assumptions'!$C$8 + 1), K$20 * $D$9)))) | ... CM21: =IF(CM$16 = "","", IF(CM$16 =( 'Model_Assumptions'!$B$8 +1), CM$20 * $E$9, IF(CM$16 <= 'Model_Assumptions'!$C$8, CM$20 * $C$9, IF(CM$16 >= ('Model_Assumptions'!$C$8 + 1), CM$20 * $D$9))))
B22: Change in Working Capital | D22: =IF(D$16="","",IF(D$16=('Model_Assumptions'!$B$8+1),( D$17-C$17)*$E$12,IF(D$16<='Model_Assumptions'!$C$8,( D$17-C$17)*$C$12,IF(D$16>=('Model_Assumptions'!$C$8 + 1), ( D$17-C$17)*$D$12, "")))) | E22: =IF(E$16="","",IF(E$16=('Model_Assumptions'!$B$8+1),( E$17-D$17)*$E$12,IF(E$16<='Model_Assumptions'!$C$8,( E$17-D$17)*$C$12,IF(E$16>=('Model_Assumptions'!$C$8 + 1), ( E$17-D$17)*$D$12, "")))) | F22: =IF(F$16="","",IF(F$16=('Model_Assumptions'!$B$8+1),( F$17-E$17)*$E$12,IF(F$16<='Model_Assumptions'!$C$8,( F$17-E$17)*$C$12,IF(F$16>=('Model_Assumptions'!$C$8 + 1), ( F$17-E$17)*$D$12, "")))) | G22: =IF(G$16="","",IF(G$16=('Model_Assumptions'!$B$8+1),( G$17-F$17)*$E$12,IF(G$16<='Model_Assumptions'!$C$8,( G$17-F$17)*$C$12,IF(G$16>=('Model_Assumptions'!$C$8 + 1), ( G$17-F$17)*$D$12, "")))) | H22: =IF(H$16="","",IF(H$16=('Model_Assumptions'!$B$8+1),( H$17-G$17)*$E$12,IF(H$16<='Model_Assumptions'!$C$8,( H$17-G$17)*$C$12,IF(H$16>=('Model_Assumptions'!$C$8 + 1), ( H$17-G$17)*$D$12, "")))) | I22: =IF(I$16="","",IF(I$16=('Model_Assumptions'!$B$8+1),( I$17-H$17)*$E$12,IF(I$16<='Model_Assumptions'!$C$8,( I$17-H$17)*$C$12,IF(I$16>=('Model_Assumptions'!$C$8 + 1), ( I$17-H$17)*$D$12, "")))) | J22: =IF(J$16="","",IF(J$16=('Model_Assumptions'!$B$8+1),( J$17-I$17)*$E$12,IF(J$16<='Model_Assumptions'!$C$8,( J$17-I$17)*$C$12,IF(J$16>=('Model_Assumptions'!$C$8 + 1), ( J$17-I$17)*$D$12, "")))) | K22: =IF(K$16="","",IF(K$16=('Model_Assumptions'!$B$8+1),( K$17-J$17)*$E$12,IF(K$16<='Model_Assumptions'!$C$8,( K$17-J$17)*$C$12,IF(K$16>=('Model_Assumptions'!$C$8 + 1), ( K$17-J$17)*$D$12, "")))) | ... CM22: =IF(CM$16="","",IF(CM$16=('Model_Assumptions'!$B$8+1),( CM$17-CL$17)*$E$12,IF(CM$16<='Model_Assumptions'!$C$8,( CM$17-CL$17)*$C$12,IF(CM$16>=('Model_Assumptions'!$C$8 + 1), ( CM$17-CL$17)*$D$12, ""))))
B23: Capital Expenditures | D23: =IF(D$16="","",IF(D$16=('Model_Assumptions'!$B$8+1), D$17*$E$13,IF(D$16<='Model_Assumptions'!$C$8,D$17*$C$13,IF(D$16>=('Model_Assumptions'!$C$8 + 1), D$17*$D$13, "")))) | E23: =IF(E$16="","",IF(E$16=('Model_Assumptions'!$B$8+1), E$17*$E$13,IF(E$16<='Model_Assumptions'!$C$8,E$17*$C$13,IF(E$16>=('Model_Assumptions'!$C$8 + 1), E$17*$D$13, "")))) | F23: =IF(F$16="","",IF(F$16=('Model_Assumptions'!$B$8+1), F$17*$E$13,IF(F$16<='Model_Assumptions'!$C$8,F$17*$C$13,IF(F$16>=('Model_Assumptions'!$C$8 + 1), F$17*$D$13, "")))) | G23: =IF(G$16="","",IF(G$16=('Model_Assumptions'!$B$8+1), G$17*$E$13,IF(G$16<='Model_Assumptions'!$C$8,G$17*$C$13,IF(G$16>=('Model_Assumptions'!$C$8 + 1), G$17*$D$13, "")))) | H23: =IF(H$16="","",IF(H$16=('Model_Assumptions'!$B$8+1), H$17*$E$13,IF(H$16<='Model_Assumptions'!$C$8,H$17*$C$13,IF(H$16>=('Model_Assumptions'!$C$8 + 1), H$17*$D$13, "")))) | I23: =IF(I$16="","",IF(I$16=('Model_Assumptions'!$B$8+1), I$17*$E$13,IF(I$16<='Model_Assumptions'!$C$8,I$17*$C$13,IF(I$16>=('Model_Assumptions'!$C$8 + 1), I$17*$D$13, "")))) | J23: =IF(J$16="","",IF(J$16=('Model_Assumptions'!$B$8+1), J$17*$E$13,IF(J$16<='Model_Assumptions'!$C$8,J$17*$C$13,IF(J$16>=('Model_Assumptions'!$C$8 + 1), J$17*$D$13, "")))) | K23: =IF(K$16="","",IF(K$16=('Model_Assumptions'!$B$8+1), K$17*$E$13,IF(K$16<='Model_Assumptions'!$C$8,K$17*$C$13,IF(K$16>=('Model_Assumptions'!$C$8 + 1), K$17*$D$13, "")))) | ... CM23: =IF(CM$16="","",IF(CM$16=('Model_Assumptions'!$B$8+1), CM$17*$E$13,IF(CM$16<='Model_Assumptions'!$C$8,CM$17*$C$13,IF(CM$16>=('Model_Assumptions'!$C$8 + 1), CM$17*$D$13, ""))))
B25: Free Cash Flow (FCF) | D25: =IF(D16="", "", D19+D21-D22-D23) | E25: =IF(E16="", "", E19+E21-E22-E23) | F25: =IF(F16="", "", F19+F21-F22-F23) | G25: =IF(G16="", "", G19+G21-G22-G23) | H25: =IF(H16="", "", H19+H21-H22-H23) | I25: =IF(I16="", "", I19+I21-I22-I23) | J25: =IF(J16="", "", J19+J21-J22-J23) | K25: =IF(K16="", "", K19+K21-K22-K23) | ... CM25: =IF(CM16="", "", CM19+CM21-CM22-CM23)
B26: Present Value of FCF | D26: =IF(OR(D16="", D$15=$E$7),"",PV($G$43,D$16,0,-D$25)) | E26: =IF(OR(E16="", E$15=$E$7),"",PV($G$43,E$16,0,-E$25)) | F26: =IF(OR(F16="", F$15=$E$7),"",PV($G$43,F$16,0,-F$25)) | G26: =IF(OR(G16="", G$15=$E$7),"",PV($G$43,G$16,0,-G$25)) | H26: =IF(OR(H16="", H$15=$E$7),"",PV($G$43,H$16,0,-H$25)) | I26: =IF(OR(I16="", I$15=$E$7),"",PV($G$43,I$16,0,-I$25)) | J26: =IF(OR(J16="", J$15=$E$7),"",PV($G$43,J$16,0,-J$25)) | K26: =IF(OR(K16="", K$15=$E$7),"",PV($G$43,K$16,0,-K$25)) | ... CM26: =IF(OR(CM16="", CM$15=$E$7),"",PV($G$43,CM$16,0,-CM$25))
B28: DCF | F28: WACC
B29: Net Present Value of FCF | C29: =SUM(OFFSET(D26,0,0,1,('Model_Assumptions'!B8))) | F29: Total Debt | G29: 98657000000
B30: Terminal Value | C30: =INDEX(B15:BI25,11,'Model_Assumptions'!B8+3)/($G$43-'Model_Assumptions'!$E$8) | F30: Current Share Price | G30: 250.12
B31: Present Value of Terminal Value | C31: =PV(H43, 'Model_Assumptions'!$B$8+1, 0, -$C$30) | F31: Weighted Average Shares Outstanding | G31: 15004697000
B32: Enterprise Value | C32: =$C$31 + $C$29 | F32: Market Value of Equity | G32: =$G$30*$G$31
F33: Weight of Equity | G33: =$G$32/($G$29+$G$32)
B34: + Excess Cash | C34: 0 | F34: Weight of Debt | G34: =$G$29/($G$29+$G$32)
B35: - Total Debt | C35: 98657000000
F36: Beta | G36: 0.01
B37: Present Value of Future Equity | C37: =$C$32+$C$34-$C$35 | F37: Risk Free Rate of Return | G37: =Model_Assumptions!$G$8
B38: Weighted Average Shares Outstanding | C38: 15004697000 | F38: Expected Market Return | G38: =Model_Assumptions!$F$8
F39: Market Risk Premium | G39: =$G$38-$G$37
B40: Expected Price Per Share | C40: =$C$37/$C$38 | F40: Expected Return of Equity | G40: =$G$38+($G$39*$G$36)
F41: Expected Cost of Debt | G41: 0
B42: Under / Over | C42: =IF((C40-G30)/G30 > 0.1, "UNDER VALUED", IF((C40-G30)/G30 < -0.1, "OVER VALUED", "FAIRLY VALUED"))
F43: WACC | G43: =($G$40*$G$33)+($G$41 * $G$34 * (1-$C$9))
